odoo8_addon_l10n_ro_account_bank_statement_import_mt940_brd-8.0.1.0.0.99.dev5-py2.7-nspkg.pth
odoo8_addon_l10n_ro_account_bank_statement_import_mt940_brd-8.0.1.0.0.99.dev5.dist-info/METADATA
odoo8_addon_l10n_ro_account_bank_statement_import_mt940_brd-8.0.1.0.0.99.dev5.dist-info/RECORD
odoo8_addon_l10n_ro_account_bank_statement_import_mt940_brd-8.0.1.0.0.99.dev5.dist-info/WHEEL
odoo8_addon_l10n_ro_account_bank_statement_import_mt940_brd-8.0.1.0.0.99.dev5.dist-info/namespace_packages.txt
odoo8_addon_l10n_ro_account_bank_statement_import_mt940_brd-8.0.1.0.0.99.dev5.dist-info/top_level.txt
odoo_addons/l10n_ro_account_bank_statement_import_mt940_brd/README.rst
odoo_addons/l10n_ro_account_bank_statement_import_mt940_brd/__init__.py
odoo_addons/l10n_ro_account_bank_statement_import_mt940_brd/__openerp__.py
odoo_addons/l10n_ro_account_bank_statement_import_mt940_brd/demo/demo_data.xml
odoo_addons/l10n_ro_account_bank_statement_import_mt940_brd/i18n/ca_ES.po
odoo_addons/l10n_ro_account_bank_statement_import_mt940_brd/i18n/de.po
odoo_addons/l10n_ro_account_bank_statement_import_mt940_brd/i18n/es.po
odoo_addons/l10n_ro_account_bank_statement_import_mt940_brd/i18n/fi.po
odoo_addons/l10n_ro_account_bank_statement_import_mt940_brd/i18n/fr.po
odoo_addons/l10n_ro_account_bank_statement_import_mt940_brd/i18n/fr_CH.po
odoo_addons/l10n_ro_account_bank_statement_import_mt940_brd/i18n/gl.po
odoo_addons/l10n_ro_account_bank_statement_import_mt940_brd/i18n/l10n_ro_account_bank_statement_import_mt940_brd.pot
odoo_addons/l10n_ro_account_bank_statement_import_mt940_brd/i18n/lt_LT.po
odoo_addons/l10n_ro_account_bank_statement_import_mt940_brd/i18n/nb_NO.po
odoo_addons/l10n_ro_account_bank_statement_import_mt940_brd/i18n/nl.po
odoo_addons/l10n_ro_account_bank_statement_import_mt940_brd/i18n/nl_NL.po
odoo_addons/l10n_ro_account_bank_statement_import_mt940_brd/i18n/pt_BR.po
odoo_addons/l10n_ro_account_bank_statement_import_mt940_brd/i18n/pt_PT.po
odoo_addons/l10n_ro_account_bank_statement_import_mt940_brd/i18n/sl.po
odoo_addons/l10n_ro_account_bank_statement_import_mt940_brd/models/__init__.py
odoo_addons/l10n_ro_account_bank_statement_import_mt940_brd/models/account_bank_statement_import.py
odoo_addons/l10n_ro_account_bank_statement_import_mt940_brd/models/mt940.py
odoo_addons/l10n_ro_account_bank_statement_import_mt940_brd/static/description/icon.png
odoo_addons/l10n_ro_account_bank_statement_import_mt940_brd/test_files/test_brd_940.txt
