Metadata-Version: 2.1
Name: odoo8-addon-l10n-ro-account-bank-statement-import-mt940-brd
Version: 8.0.1.0.0.99.dev5
Summary: MT940 BRD Format Bank Statements Import
Home-page: https://www.forbiom.eu
Author: Forest and Biomass Services Romania, Odoo Community Association (OCA)
Author-email: support@odoo-community.org
License: AGPL-3
Platform: UNKNOWN
Classifier: Programming Language :: Python
Classifier: Framework :: Odoo
Classifier: License :: OSI Approved :: GNU Affero General Public License v3
Requires-Python: ~=2.7
Requires-Dist: odoo8-addon-account-bank-statement-import-mt940-base
Requires-Dist: odoo (<9.0a,>=8.0a)
